election_loader/__init__.py
election_loader/apps.py
election_loader/authentication.py
election_loader/celery.py
election_loader/urls.py
election_loader/views.py
election_loader/admin/__init__.py
election_loader/admin/loader_token.py
election_loader/loaders/__init__.py
election_loader/loaders/election.py
election_loader/migrations/0001_initial.py
election_loader/migrations/0002_auto_20190829_1927.py
election_loader/migrations/0003_auto_20190829_1929.py
election_loader/migrations/__init__.py
election_loader/models/__init__.py
election_loader/models/loader_token.py
election_loader/serializers/__init__.py
election_loader/serializers/division.py
election_loader/serializers/election.py
election_loader/serializers/loader_token.py
election_loader/serializers/party.py
election_loader/serializers/state.py
election_loader/tasks/__init__.py
election_loader/tasks/process_metadata.py
election_loader/tests/__init__.py
election_loader/tests/test__process_metadata.py
election_loader/utils/__init__.py
election_loader/utils/api_auth.py
election_loader/utils/lookups/__init__.py
election_loader/utils/lookups/election.py
election_loader/utils/lookups/geography.py
election_loader/utils/lookups/government.py
election_loader/viewsets/__init__.py
election_loader/viewsets/state.py
politico_civic_election_loader-1.0a8.dev1.dist-info/LICENSE
politico_civic_election_loader-1.0a8.dev1.dist-info/METADATA
politico_civic_election_loader-1.0a8.dev1.dist-info/WHEEL
politico_civic_election_loader-1.0a8.dev1.dist-info/top_level.txt
politico_civic_election_loader-1.0a8.dev1.dist-info/RECORD
