Metadata-Version: 2.1
Name: politico-civic-election-loader
Version: 1.0a8.dev1
Summary: Ingest election metadata and results from outside sources, the POLITICO way.
Home-page: https://github.com/The-Politico/politico-civic-election-loader/
Author: POLITICO interactive news
Author-email: interactives@politico.com
License: MIT
Download-URL: https://github.com/The-Politico/politico-civic-election-loader/archive/1.0a8.dev1.tar.gz
Platform: UNKNOWN
Classifier: Development Status :: 3 - Alpha
Classifier: Framework :: Django
Classifier: Framework :: Django :: 2.0
Classifier: Intended Audience :: Developers
Classifier: Intended Audience :: Information Technology
Classifier: License :: OSI Approved :: MIT License
Classifier: Operating System :: OS Independent
Classifier: Programming Language :: Python :: 3
Classifier: Programming Language :: Python :: 3.5
Classifier: Programming Language :: Python :: 3.6
Classifier: Topic :: Internet :: WWW/HTTP
Requires-Dist: celery
Requires-Dist: django
Requires-Dist: djangorestframework
Requires-Dist: psycopg2-binary
Requires-Dist: politico-civic-utils
Requires-Dist: politico-civic-entity
Requires-Dist: politico-civic-geography
Requires-Dist: politico-civic-government
Requires-Dist: politico-civic-election
Requires-Dist: us
Provides-Extra: test
Requires-Dist: pytest ; extra == 'test'
